[
    {
        "name": "Hermelin",
        "url": "http://wiki.wargaming.net/en/Ship:Hermelin"
    },
    {
        "name": "Dresden",
        "url": "http://wiki.wargaming.net/en/Ship:Dresden"
    },
    {
        "name": "Emden",
        "url": "http://wiki.wargaming.net/en/Ship:Emden"
    },
    {
        "name": "Kolberg",
        "url": "http://wiki.wargaming.net/en/Ship:Kolberg"
    },
    {
        "name": "Karlsruhe",
        "url": "http://wiki.wargaming.net/en/Ship:Karlsruhe"
    },
    {
        "name": "Königsberg",
        "url": "http://wiki.wargaming.net/en/Ship:K%C3%B6nigsberg"
    },
    {
        "name": "Nürnberg",
        "url": "http://wiki.wargaming.net/en/Ship:N%C3%BCrnberg"
    },
    {
        "name": "Admiral Graf Spee",
        "url": "http://wiki.wargaming.net/en/Ship:Admiral_Graf_Spee"
    },
    {
        "name": "HSF Admiral Graf Spee",
        "url": "http://wiki.wargaming.net/en/Ship:HSF_Admiral_Graf_Spee"
    },
    {
        "name": "Yorck",
        "url": "http://wiki.wargaming.net/en/Ship:Yorck"
    },
    {
        "name": "Admiral Hipper",
        "url": "http://wiki.wargaming.net/en/Ship:Admiral_Hipper"
    },
    {
        "name": "Prinz Eugen",
        "url": "http://wiki.wargaming.net/en/Ship:Prinz_Eugen"
    },
    {
        "name": "Roon",
        "url": "http://wiki.wargaming.net/en/Ship:Roon"
    },
    {
        "name": "Siegfried",
        "url": "http://wiki.wargaming.net/en/Ship:Siegfried"
    },
    {
        "name": "Hindenburg",
        "url": "http://wiki.wargaming.net/en/Ship:Hindenburg"
    }
]